[
  {
    "name": "Plastron noir",
    "cost": 1,
    "effect": "Le champion gagne +2 PV et ignore les dégâts infligés par des compagnons.",
    "type": "Equipement",
    "speed": 8
  },
  {
    "name": "Insigne de la Black Watch",
    "cost": 1,
    "effect": "Pour chaque champion en vie dans votre équipe, inflige 2 dégâts au champion adverse.",
    "type": "Pouvoir",
    "speed": 3
  },
  {
    "name": "Frappe frontale",
    "cost": 1,
    "effect": "Inflige l’attaque du champion au champion adverse.",
    "type": "Pouvoir",
    "speed": 8
  },
  {
    "name": "Gestion",
    "cost": 1,
    "effect": "Mélangez les cartes de votre défausse avec votre deck, puis piochez 1 carte.",
    "type": "Pouvoir",
    "speed": 3
  },
  {
    "name": "Épée fraîchement forgée",
    "cost": 1,
    "effect": "Augmente l’attaque du champion de +1.",
    "type": "Equipement",
    "speed": 6
  },
  {
    "name": "Réparation",
    "cost": 2,
    "effect": "Allez chercher une carte équipement dans la défausse et équipez-la immédiatement au champion en ignorant son coût.",
    "type": "Instantanee",
    "speed": "X"
  }
]
